semanticscholar/ApiRequester.py
semanticscholar/AsyncSemanticScholar.py
semanticscholar/Author.py
semanticscholar/BaseReference.py
semanticscholar/Citation.py
semanticscholar/Journal.py
semanticscholar/PaginatedResults.py
semanticscholar/Paper.py
semanticscholar/PublicationVenue.py
semanticscholar/Reference.py
semanticscholar/SemanticScholar.py
semanticscholar/SemanticScholarException.py
semanticscholar/SemanticScholarObject.py
semanticscholar/Tldr.py
semanticscholar/__init__.py
semanticscholar-0.9.0.dist-info/LICENSE
semanticscholar-0.9.0.dist-info/METADATA
semanticscholar-0.9.0.dist-info/WHEEL
semanticscholar-0.9.0.dist-info/top_level.txt
semanticscholar-0.9.0.dist-info/RECORD
