Metadata-Version: 2.1
Name: semanticscholar
Version: 0.9.0
Summary: Unofficial Python client library for Semantic Scholar APIs.
Home-page: http://danielnsilva.com/semanticscholar
Author: Daniel Silva
Author-email: danielnsilva@gmail.com
License: MIT
Classifier: Development Status :: 4 - Beta
Classifier: Intended Audience :: Developers
Classifier: Intended Audience :: Science/Research
Classifier: License :: OSI Approved :: MIT License
Classifier: Programming Language :: Python
Classifier: Programming Language :: Python :: 3
Classifier: Programming Language :: Python :: 3.8
Classifier: Programming Language :: Python :: 3.9
Classifier: Programming Language :: Python :: 3.10
Classifier: Programming Language :: Python :: 3.11
Classifier: Programming Language :: Python :: 3.12
Classifier: Topic :: Software Development :: Libraries :: Python Modules
Requires-Python: >=3.8
License-File: LICENSE
Requires-Dist: tenacity
Requires-Dist: httpx
Requires-Dist: nest_asyncio
